{
	"repository": "https://github.com/llenotre/maestro",
	"compilation": {
		"environment": [
			{
				"name": "PATH",
				"value": "/bin:/usr/bin"
			},
			{
				"name": "KERNEL_MODE",
				"value": "debug"
			},
			{
				"name": "KERNEL_TEST",
				"value": "true"
			}
		],
		"command": "make",
		"arguments": []
	},
	"output_binary": "maestro.iso",
	"test_machines": [
		{
			"name": "foo",
			"broadcast_address": "0.0.0.0",
			"mac": "00:00:00:00:00:00",
			"gpio": 0,
			"boot_delay": 0,
			"boot_timeout": 0
		}
	]
}
